{
	"backtraceGraph" : 
	{
		"commands" : 
		[
			"install",
			"vci_add_executable"
		],
		"files" : 
		[
			"cmake-library/VCI/VCICommon.cmake",
			"src/OpenMesh/Apps/Subdivider/commandlineAdaptiveSubdivider/CMakeLists.txt"
		],
		"nodes" : 
		[
			{
				"file" : 1
			},
			{
				"command" : 1,
				"file" : 1,
				"line" : 8,
				"parent" : 0
			},
			{
				"command" : 0,
				"file" : 0,
				"line" : 231,
				"parent" : 1
			}
		]
	},
	"installers" : 
	[
		{
			"backtrace" : 2,
			"component" : "Unspecified",
			"destination" : "bin",
			"paths" : 
			[
				"Build/bin/commandlineAdaptiveSubdivider"
			],
			"targetId" : "commandlineAdaptiveSubdivider::@df5da50b4158fd8eba50",
			"targetIndex" : 9,
			"type" : "target"
		}
	],
	"paths" : 
	{
		"build" : "src/OpenMesh/Apps/Subdivider/commandlineAdaptiveSubdivider",
		"source" : "src/OpenMesh/Apps/Subdivider/commandlineAdaptiveSubdivider"
	}
}
